transigner/align.py
transigner/em.py
transigner/opts.py
transigner/pre.py
transigner/run_transigner.py
transigner/utils.py
transigner-1.1.2.data/data/bin/em
transigner-1.1.2.dist-info/METADATA
transigner-1.1.2.dist-info/WHEEL
transigner-1.1.2.dist-info/entry_points.txt
transigner-1.1.2.dist-info/top_level.txt
transigner-1.1.2.dist-info/RECORD
