Metadata-Version: 2.2
Name: transigner
Version: 1.1.2
Summary: assign long RNA-seq reads to transcripts
Home-page: https://github.com/haydenji0731/transigner
Author: Hyun Joo Ji
Author-email: hji20@jh.edu
Requires-Python: >=3.8
Dynamic: author
Dynamic: author-email
Dynamic: description
Dynamic: description-content-type
Dynamic: home-page
Dynamic: requires-python
Dynamic: summary
